caw062_first_package/__init__.py
caw062_first_package/add.py
caw062_first_package/subtract.py
caw062_first_package/extras/__init__.py
caw062_first_package/extras/divide.py
caw062_first_package/extras/multiply.py
caw062_first_package-0.0.4.dist-info/METADATA
caw062_first_package-0.0.4.dist-info/WHEEL
caw062_first_package-0.0.4.dist-info/top_level.txt
caw062_first_package-0.0.4.dist-info/RECORD
